{"nodes": [0, 1, 2, 3, 4, 5, 6, 7, 8, 9], "edges": [[0, 1], [0, 2], [0, 3], [0, 4], [0, 6], [0, 7], [0, 9], [1, 3], [1, 8], [2, 6], [3, 4], [3, 5], [3, 7], [4, 5], [4, 8], [5, 9]], "nodes-metadata": [[0, {"name": "Charles Colon", "like-music": ["metal", "rock", "hip-hop", "punk", "gospel", "techno"], "like-movies": ["comedy", "action", "horror", "fantasy", "animation"]}], [1, {"name": "Garrett Erickson", "like-music": ["punk", "soul", "country", "electronic", "classic", "rock", "reggae", "jazz", "hip-hop", "pop", "folk", "indie", "metal", "techno", "house", "latin", "gospel", "blues"], "like-movies": ["action"]}], [2, {"name": "Ricardo Morris", "like-music": ["jazz", "rock"], "like-movies": ["horror", "animation"]}], [3, {"name": "Whitney Perez", "like-music": ["blues", "gospel", "reggae", "latin", "classic", "house", "country", "indie", "jazz", "soul", "metal"], "like-movies": ["action", "animation", "horror"]}], [4, {"name": "Joshua Smith", "like-music": ["hip-hop", "reggae", "latin", "gospel", "pop", "folk", "blues", "jazz", "soul", "punk", "rock", "techno"], "like-movies": ["fantasy", "horror", "action", "comedy"]}], [5, {"name": "Cathy Miles", "like-music": ["hip-hop", "gospel", "punk", "jazz", "pop", "reggae", "blues", "techno", "house", "indie", "rock", "soul", "latin", "metal", "folk", "electronic", "classic"], "like-movies": ["action", "fantasy", "animation"]}], [6, {"name": "Joshua Wheeler", "like-music": ["metal", "rock", "soul", "indie", "punk", "blues", "techno"], "like-movies": ["fantasy"]}], [7, {"name": "William Erickson", "like-music": ["country", "pop"], "like-movies": ["fantasy", "comedy", "horror"]}], [8, {"name": "Natalie Martinez", "like-music": ["reggae"], "like-movies": ["action", "animation"]}], [9, {"name": "Joseph Cobb", "like-music": ["pop", "folk", "rock", "house", "indie", "jazz", "classic", "techno", "soul", "reggae", "electronic", "metal"], "like-movies": ["fantasy", "comedy"]}]], "edges-metadata": [[0, 1, {}], [0, 2, {}], [0, 3, {}], [0, 4, {}], [0, 6, {}], [0, 7, {}], [0, 9, {}], [1, 3, {}], [1, 8, {}], [2, 6, {}], [3, 4, {}], [3, 5, {}], [3, 7, {}], [4, 5, {}], [4, 8, {}], [5, 9, {}]], "neighbors": {"0": [1, 2, 3, 4, 6, 7, 9], "1": [0, 3, 8], "2": [0, 6], "3": [0, 1, 4, 5, 7], "4": [0, 3, 5, 8], "5": [3, 4, 9], "6": [0, 2], "7": [0, 3], "8": [1, 4], "9": [0, 5]}}